wangfan.py
wangfan-2.0.dist-info/METADATA
wangfan-2.0.dist-info/WHEEL
wangfan-2.0.dist-info/top_level.txt
wangfan-2.0.dist-info/RECORD
