Metadata-Version: 2.1
Name: wangfan
Version: 2.0
Summary: 617
Home-page: UNKNOWN
Author: fan
Author-email: 2061156797@qq.com
License: UNKNOWN
Platform: UNKNOWN
